contractshield/__init__.py
contractshield/cel/__init__.py
contractshield/cel/evaluator.py
contractshield/core/__init__.py
contractshield/core/contract.py
contractshield/core/errors.py
contractshield/core/result.py
contractshield/core/validator.py
contractshield/fastapi/__init__.py
contractshield/fastapi/middleware.py
contractshield/openapi/__init__.py
contractshield/openapi/loader.py
contractshield/vulnerability/__init__.py
contractshield/vulnerability/command.py
contractshield/vulnerability/nosql.py
contractshield/vulnerability/path_traversal.py
contractshield/vulnerability/prototype.py
contractshield/vulnerability/scanner.py
contractshield/vulnerability/sqli.py
contractshield/vulnerability/ssrf.py
contractshield/vulnerability/xss.py
contractshield-1.5.4.dist-info/METADATA
contractshield-1.5.4.dist-info/WHEEL
contractshield-1.5.4.dist-info/top_level.txt
contractshield-1.5.4.dist-info/RECORD
