Metadata-Version: 2.4
Name: contractshield
Version: 1.5.4
Summary: Contract-First API Security for Python
Author-email: ContractShield <contact@contractshield.dev>
License: Apache-2.0
Project-URL: Homepage, https://contractshield.dev
Project-URL: Documentation, https://docs.contractshield.dev
Project-URL: Repository, https://github.com/zeekmartin/contractshield
Project-URL: Issues, https://github.com/zeekmartin/contractshield
Keywords: api,security,validation,openapi,fastapi,contract
Classifier: Development Status :: 4 - Beta
Classifier: Framework :: FastAPI
Classifier: Framework :: Flask
Classifier: Intended Audience :: Developers
Classifier: License :: OSI Approved :: Apache Software License
Classifier: Programming Language :: Python :: 3
Classifier: Programming Language :: Python :: 3.9
Classifier: Programming Language :: Python :: 3.10
Classifier: Programming Language :: Python :: 3.11
Classifier: Programming Language :: Python :: 3.12
Classifier: Topic :: Security
Classifier: Topic :: Internet :: WWW/HTTP :: HTTP Servers
Classifier: Typing :: Typed
Requires-Python: >=3.9
Requires-Dist: jsonschema>=4.20.0
Requires-Dist: pyyaml>=6.0
Requires-Dist: httpx>=0.25.0
Provides-Extra: fastapi
Requires-Dist: fastapi>=0.104.0; extra == "fastapi"
Requires-Dist: starlette>=0.27.0; extra == "fastapi"
Provides-Extra: flask
Requires-Dist: flask>=3.0.0; extra == "flask"
Provides-Extra: cel
Requires-Dist: cel-python>=0.1.5; extra == "cel"
Provides-Extra: all
Requires-Dist: fastapi>=0.104.0; extra == "all"
Requires-Dist: starlette>=0.27.0; extra == "all"
Requires-Dist: flask>=3.0.0; extra == "all"
Requires-Dist: cel-python>=0.1.5; extra == "all"
Provides-Extra: dev
Requires-Dist: pytest>=7.4.0; extra == "dev"
Requires-Dist: pytest-asyncio>=0.21.0; extra == "dev"
Requires-Dist: pytest-cov>=4.1.0; extra == "dev"
Requires-Dist: black>=23.0.0; extra == "dev"
Requires-Dist: ruff>=0.1.0; extra == "dev"
Requires-Dist: mypy>=1.6.0; extra == "dev"
Requires-Dist: httpx>=0.25.0; extra == "dev"
